[
	{
		"title" : "Data science is the process of diverse set of data through ?",
		"detail" : "",
		"output" : "All of the above",
		"options" : {
			"a" : "organizing data",
			"b" : "processing data",
			"c" : "analysing data",
			"d" : "All of the above"
		},
		"correct": "D"
	},

		{
		"title" : "The modern conception of data science as an independent discipline is sometimes attributed to?",
		"detail" : "",
		"output" : "William S",
		"options" : {
			"a" : "William S",
			"b" : "John McCarthy",
			"c" : "Arthur Samuel",
			"d" : "Satoshi Nakamoto"
		},
		"correct": "A"
	},

		{
		"title" : "Which of the following language is used in Data science?",
		"detail" : "",
		"output" : "R",
		"options" : {
			"a" : "C",
			"b" : "C++",
			"c" : "R",
			"d" : "Ruby"
		},
		"correct": "C"
	},

		{
		"title" : "Which of the following is false?",
		"detail" : "",
		"output" : "Raw data should be processed only one time.",
		"options" : {
			"a" : "Subsetting can be used to select and exclude variables and observationsk",
			"b" : "Raw data should be processed only one time.",
			"c" : "Merging concerns combining datasets on the same observations to produce a result with more variables",
			"d" : "None Of the above"
		},
		"correct": "B"
	},

		{
		"title" : "What is the work of Data Architect?",
		"detail" : "",
		"output" : "build data solutions that are optimized for performance and design applications",
		"options" : {
			"a" : "utilize large data sets to gather information that meets their company's needs",
			"b" : "work with businesses to determine the best usage of the information yielded from data",
			"c" : "build data solutions that are optimized for performance and design applications",
			"d" : "All of the above"
		},
		"correct": "C"
	},

		{
		"title" : "Which of the following is correct skills for a Data Scientist?",
		"detail" : "",
		"output" : "All of the above",
		"options" : {
			"a" : "Probability & Statistics",
			"b" : "Machine Learning / Deep Learning",
			"c" : "Data Wrangling",
			"d" : "All of the above"
		},
		"correct": "D"
	},

		{
		"title" : "Which of the following are correct component for data science?",
		"detail" : "",
		"output" : "All of the above",
		"options" : {
			"a" : "Data Engineering",
			"b" : "Advanced Computing",
			"c" : "Domain expertise",
			"d" : "All of the above"
		},
		"correct": "D"
	},

		{
		"title" : "Which of the following is not a part of data science process?",
		"detail" : "",
		"output" : "Communication Building",
		"options" : {
			"a" : "Discovery",
			"b" : "Model Planning",
			"c" : "Communication Building",
			"d" : "Operationalize"
		},
		"correct": "C"
	},

	{
		"title" : "Which of the following are the Data Sources in data science?",
		"detail" : "",
		"output" : "Both A and B",
		"options" : {
			"a" : "Structured",
			"b" : "UnStructured",
			"c" : "Both A and B",
			"d" : "None of the above"
		},
		"correct": "C"
	},

		{
		"title" : "Which of the following is not a application for data science?",
		"detail" : "",
		"output" : "Privacy Checker",
		"options" : {
			"a" : "Recommendation Systems",
			"b" : "Image & Speech Recognition",
			"c" : "Online Price Comparison",
			"d" : "Privacy Checker"
		},
		"correct": "D"
	},

		{
		"title" : "Point out the correct statement.",
		"detail" : "",
		"output" : "Raw data is original source of data",
		"options" : {
			"a" : "Raw data is original source of data",
			"b" : "Preprocessed data is original source of data",
			"c" : "Raw data is the data obtained after processing steps",
			"d" : "None of the above"
		},
		"correct": "A"
	},

	

		{
		"title" : "Which of the following is one of the key data science skills?",
		"detail" : "",
		"output" : "All of the above",
		"options" : {
			"a" : "Statistics",
			"b" : "Machine Learning",
			"c" : "Data Visualization",
			"d" : "All of the above"
		},
		"correct": "D"
	},

		{
		"title" : "Which of the following is a key characteristic of a hacker?",
		"detail" : "",
		"output" : "Willing to find answers on their own",
		"options" : {
			"a" : "Afraid to say they don't know the answer",
			"b" : "Willing to find answers on their own",
			"c" : "Not Willing to find answers on their own",
			"d" : "All of the above"
		},
		"correct": "B"
	},
	


	{
		"title" : "Raw data should be processed only one time.",
		"detail" : "",
		"output" : "False",
		"options" : {
			"a" : "True",
			"b" : "False",
			"c" : "Can be true or false",
			"d" : "Can not say"
		},
		"correct": "B"
	},

		{
		"title" : "Which of the following is the common goal of statistical modelling?",
		"detail" : "",
		"output" : "Inference",
		"options" : {
			"a" : "Inference",
			"b" : "Summarizing",
			"c" : " Subsetting",
			"d" : "None of the above"
		},
		"correct": "A"
	},
    {
		"title" : "Causal analysis is commonly applied to census data.",
		"detail" : "",
		"output" : "False",
		"options" : {
			"a" : "True",
			"b" : "False",
			"c" : "Can be true or false",
			"d" : "Can not say"
		},
		"correct": "B"
	}

		

]